tacoma/__init__.py
tacoma/interpolator.py
tacoma/metrics.py
tacoma/rom.py
tacoma/utils.py
Tacoma_lib-1.0.1.dist-info/LICENSE
Tacoma_lib-1.0.1.dist-info/METADATA
Tacoma_lib-1.0.1.dist-info/WHEEL
Tacoma_lib-1.0.1.dist-info/top_level.txt
Tacoma_lib-1.0.1.dist-info/RECORD
