Metadata-Version: 2.1
Name: Tacoma-lib
Version: 1.0.1
Summary: TACOMA lib
Author: Jaime Bowen Varela, Rodrigo Castellanos, Alejandro Gorgues
Author-email: jbowvar@inta.es, rcasgar@inta.es, gorguesva@inta.es
License-File: LICENSE
Requires-Dist: pandas (>=1.3.5)
Requires-Dist: numpy (>=1.21.6)
Requires-Dist: scipy (>=1.4.1)
Requires-Dist: scikit-learn (>=1.0.2)
Requires-Dist: matplotlib (>=3.5.0)
